wrapclib/__init__.py
wrapclib/re2/__init__.py
wrapclib/re2/_re2.cc
wrapclib/re2/_re2.cpython-38-darwin.so
wrapclib/re2/re2.py
wrapclib/re2/gitsrc/re2/bitmap256.h
wrapclib/re2/gitsrc/re2/bitstate.cc
wrapclib/re2/gitsrc/re2/compile.cc
wrapclib/re2/gitsrc/re2/dfa.cc
wrapclib/re2/gitsrc/re2/filtered_re2.cc
wrapclib/re2/gitsrc/re2/filtered_re2.h
wrapclib/re2/gitsrc/re2/mimics_pcre.cc
wrapclib/re2/gitsrc/re2/nfa.cc
wrapclib/re2/gitsrc/re2/onepass.cc
wrapclib/re2/gitsrc/re2/parse.cc
wrapclib/re2/gitsrc/re2/perl_groups.cc
wrapclib/re2/gitsrc/re2/pod_array.h
wrapclib/re2/gitsrc/re2/prefilter.cc
wrapclib/re2/gitsrc/re2/prefilter.h
wrapclib/re2/gitsrc/re2/prefilter_tree.cc
wrapclib/re2/gitsrc/re2/prefilter_tree.h
wrapclib/re2/gitsrc/re2/prog.cc
wrapclib/re2/gitsrc/re2/prog.h
wrapclib/re2/gitsrc/re2/re2.cc
wrapclib/re2/gitsrc/re2/re2.h
wrapclib/re2/gitsrc/re2/regexp.cc
wrapclib/re2/gitsrc/re2/regexp.h
wrapclib/re2/gitsrc/re2/set.cc
wrapclib/re2/gitsrc/re2/set.h
wrapclib/re2/gitsrc/re2/simplify.cc
wrapclib/re2/gitsrc/re2/sparse_array.h
wrapclib/re2/gitsrc/re2/sparse_set.h
wrapclib/re2/gitsrc/re2/stringpiece.cc
wrapclib/re2/gitsrc/re2/stringpiece.h
wrapclib/re2/gitsrc/re2/tostring.cc
wrapclib/re2/gitsrc/re2/unicode_casefold.cc
wrapclib/re2/gitsrc/re2/unicode_casefold.h
wrapclib/re2/gitsrc/re2/unicode_groups.cc
wrapclib/re2/gitsrc/re2/unicode_groups.h
wrapclib/re2/gitsrc/re2/walker-inl.h
wrapclib/re2/gitsrc/util/benchmark.h
wrapclib/re2/gitsrc/util/flags.h
wrapclib/re2/gitsrc/util/logging.h
wrapclib/re2/gitsrc/util/malloc_counter.h
wrapclib/re2/gitsrc/util/mix.h
wrapclib/re2/gitsrc/util/mutex.h
wrapclib/re2/gitsrc/util/pcre.h
wrapclib/re2/gitsrc/util/rune.cc
wrapclib/re2/gitsrc/util/strutil.cc
wrapclib/re2/gitsrc/util/strutil.h
wrapclib/re2/gitsrc/util/test.h
wrapclib/re2/gitsrc/util/utf.h
wrapclib/re2/gitsrc/util/util.h
wrapclib-0.1.71.dist-info/LICENSE.txt
wrapclib-0.1.71.dist-info/METADATA
wrapclib-0.1.71.dist-info/WHEEL
wrapclib-0.1.71.dist-info/top_level.txt
wrapclib-0.1.71.dist-info/RECORD
