Metadata-Version: 2.1
Name: wrapclib
Version: 0.1.71
Summary: Python Wrapper for some C libraries.
Home-page: http://www.xavierdupre.fr/app/wrapclib/helpsphinx/index.html
Author: Xavier Dupré
Author-email: xavier.dupre@gmail.com
License: MIT
Download-URL: https://github.com/sdpython/wrapclib/
Keywords: wrapclib,Xavier Dupré
Platform: UNKNOWN
Classifier: Programming Language :: Python :: 3
Classifier: Intended Audience :: Developers
Classifier: Topic :: Scientific/Engineering
Classifier: Topic :: Education
Classifier: License :: OSI Approved :: MIT License
Classifier: Development Status :: 5 - Production/Stable
Requires-Dist: pybind11
